udemy/__init__.py
udemy/_auth.py
udemy/_compat.py
udemy/_extract.py
udemy/_getpass.py
udemy/_internal.py
udemy/_progress.py
udemy/_sanitize.py
udemy/_session.py
udemy/_shared.py
udemy/_udemy.py
udemy/_utils.py
udemy/_vtt2srt.py
udemy/_colorized/__init__.py
udemy/_colorized/banner.py
udemy/_colorized/colors.py
udemy_dl2-0.5.data/scripts/udemy-dl
udemy_dl2-0.5.dist-info/LICENSE
udemy_dl2-0.5.dist-info/METADATA
udemy_dl2-0.5.dist-info/WHEEL
udemy_dl2-0.5.dist-info/top_level.txt
udemy_dl2-0.5.dist-info/RECORD
